flink_ml_framework/__init__.py
flink_ml_framework/context.py
flink_ml_framework/java_file.py
flink_ml_framework/java_file_c.cpython-36m-darwin.so
flink_ml_framework/node_pb2.py
flink_ml_framework/node_service_pb2.py
flink_ml_framework/node_service_pb2_grpc.py
flink_ml_framework/startup.py
flink_ml_framework/version.py
flink_ml_framework_nightly-0.4.dev20220123.dist-info/METADATA
flink_ml_framework_nightly-0.4.dev20220123.dist-info/WHEEL
flink_ml_framework_nightly-0.4.dev20220123.dist-info/top_level.txt
flink_ml_framework_nightly-0.4.dev20220123.dist-info/RECORD
